LICENSE
MANIFEST.in
README.md
setup.py
threebean_tahrir_theme/__init__.py
threebean_tahrir_theme.egg-info/PKG-INFO
threebean_tahrir_theme.egg-info/SOURCES.txt
threebean_tahrir_theme.egg-info/dependency_links.txt
threebean_tahrir_theme.egg-info/not-zip-safe
threebean_tahrir_theme.egg-info/top_level.txt
threebean_tahrir_theme/static/css/monokai.css
threebean_tahrir_theme/static/css/tahrir.css
threebean_tahrir_theme/static/css/unsemantic-grid-mobile.css
threebean_tahrir_theme/static/css/unsemantic-grid-responsive-tablet.css
threebean_tahrir_theme/static/css/unsemantic-grid-responsive.css
threebean_tahrir_theme/static/img/404.png
threebean_tahrir_theme/static/img/404.svg
threebean_tahrir_theme/static/img/500.png
threebean_tahrir_theme/static/img/500.svg
threebean_tahrir_theme/static/img/badge.png
threebean_tahrir_theme/static/img/badge_bullet.png
threebean_tahrir_theme/static/img/badge_bullet_fedora.png
threebean_tahrir_theme/static/img/badger_avatar.png
threebean_tahrir_theme/static/img/badger_avatar.svg
threebean_tahrir_theme/static/img/favicon.ico
threebean_tahrir_theme/static/img/fedora_logo.png
threebean_tahrir_theme/static/img/threebean-logo.png
threebean_tahrir_theme/static/js/builder.js
threebean_tahrir_theme/static/js/social.js