Metadata-Version: 1.0
Name: threebean-tahrir-theme
Version: 0.0.1
Summary: threebean.org theme for the Tahrir Open Badges webapp
Home-page: https://github.com/ralphbean/threebean-tahrir-theme
Author: Ralph Bean
Author-email: rbean@redhat.com
License: GPLv3+
Platform: UNKNOWN
